xrl/__init__.py
xrl/fixed_window.py
xrl/py.typed
xrl/token_bucket.py
xrl_python-0.2.0.dist-info/METADATA
xrl_python-0.2.0.dist-info/WHEEL
xrl_python-0.2.0.dist-info/RECORD
