Metadata-Version: 2.1
Name: xrl-python
Version: 0.2.0
Summary: eXtended Rate Limiter - A distributed rate limiter with multiple algorithms (Token Bucket and Fixed Window)
Home-page: https://github.com/xnog/xrl-python
License: MIT
Keywords: rate-limiting,redis,distributed,token-bucket,fixed-window,async
Author: Felipe Nogueira Gaudio
Author-email: xnogueira@gmail.com
Maintainer: Felipe Nogueira Gaudio
Maintainer-email: xnogueira@gmail.com
Requires-Python: >=3.9,<4.0
Classifier: Development Status :: 4 - Beta
Classifier: Intended Audience :: Developers
Classifier: License :: OSI Approved :: MIT License
Classifier: Operating System :: OS Independent
Classifier: Programming Language :: Python :: 3
Classifier: Programming Language :: Python :: 3.9
Classifier: Programming Language :: Python :: 3.10
Classifier: Programming Language :: Python :: 3.11
Classifier: Programming Language :: Python :: 3.12
Classifier: Programming Language :: Python :: 3.13
Classifier: Topic :: Software Development :: Libraries :: Python Modules
Classifier: Topic :: System :: Distributed Computing
Requires-Dist: redis[hiredis] (>=5.0,<7.0)
Project-URL: Documentation, https://github.com/xnog/xrl-python#readme
Project-URL: Repository, https://github.com/xnog/xrl-python
